hatch_meson/__init__.py
hatch_meson/_tags.py
hatch_meson/_version.py
hatch_meson/config.py
hatch_meson/hooks.py
hatch_meson/plugin.py
hatch_meson-0.1.0.dist-info/METADATA
hatch_meson-0.1.0.dist-info/WHEEL
hatch_meson-0.1.0.dist-info/entry_points.txt
hatch_meson-0.1.0.dist-info/licenses/LICENSE
hatch_meson-0.1.0.dist-info/RECORD
