Metadata-Version: 2.4
Name: hatch-meson
Version: 0.1.0
Summary: Hatchling plugin for building extensions via meson
Project-URL: Tracker, https://github.com/virtuald/hatch-meson/issues
Project-URL: Source, https://github.com/virtuald/hatch-meson
Author-email: Dustin Spicuzza <dustin@virtualroadside.com>
License-Expression: MIT
License-File: LICENSE
Keywords: hatch,meson
Classifier: Framework :: Hatch
Classifier: Topic :: Software Development :: Build Tools
Requires-Python: >=3.8
Requires-Dist: hatchling>=1.24.1
Requires-Dist: meson>=0.64.0; python_version < '3.12'
Requires-Dist: meson>=1.2.3; python_version >= '3.12'
Requires-Dist: validobj
Provides-Extra: test
Requires-Dist: build; extra == 'test'
Requires-Dist: cython>=3.0.3; extra == 'test'
Requires-Dist: editables; extra == 'test'
Requires-Dist: packaging>=23.1; extra == 'test'
Requires-Dist: pytest-cov[toml]; extra == 'test'
Requires-Dist: pytest-mock; extra == 'test'
Requires-Dist: pytest>=6.0; extra == 'test'
Requires-Dist: typing-extensions>=3.7.4; (python_version < '3.11') and extra == 'test'
Requires-Dist: wheel; extra == 'test'
